sec_to_HMS/__init__.py
sec_to_HMS/sec_to_hms.py
sec_to_HMS-0.0.3.1.dist-info/LICENSE.txt
sec_to_HMS-0.0.3.1.dist-info/METADATA
sec_to_HMS-0.0.3.1.dist-info/WHEEL
sec_to_HMS-0.0.3.1.dist-info/top_level.txt
sec_to_HMS-0.0.3.1.dist-info/RECORD
