Metadata-Version: 2.1
Name: sec-to-HMS
Version: 0.0.3.1
Summary: 将秒转换为时、分、秒格式
Home-page: 
Author: junchen
Author-email: rongjvzhou@outlook.com
Classifier: Programming Language :: Python :: 3
Classifier: License :: OSI Approved :: MIT License
Classifier: Operating System :: OS Independent
Requires-Python: >=3.6
License-File: LICENSE.txt
